Metadata-Version: 2.4
Name: signify
Version: 0.9.2
Summary: Module to generate and verify PE signatures
Author-email: Ralph Broenink <ralph@ralphbroenink.net>
License-Expression: MIT
Project-URL: Documentation, http://signify.readthedocs.io/en/latest/
Project-URL: Repository, https://github.com/ralphje/signify
Project-URL: Changelog, https://signify.readthedocs.io/en/latest/changelog.html
Keywords: authenticode,authentihash,fingerprinter,pe
Classifier: Development Status :: 4 - Beta
Classifier: Environment :: Console
Classifier: Intended Audience :: Developers
Classifier: Intended Audience :: Legal Industry
Classifier: Intended Audience :: System Administrators
Classifier: Programming Language :: Python
Classifier: Topic :: Scientific/Engineering :: Information Analysis
Classifier: Topic :: Security :: Cryptography
Classifier: Topic :: System :: Software Distribution
Classifier: Topic :: Utilities
Requires-Python: >=3.9
License-File: LICENSE
Requires-Dist: certvalidator>=0.11
Requires-Dist: asn1crypto<2,>=1.3
Requires-Dist: oscrypto<2,>=1.1
Requires-Dist: mscerts
Requires-Dist: typing_extensions>=4.6.0
Provides-Extra: msi
Requires-Dist: olefile; extra == "msi"
Provides-Extra: full
Requires-Dist: olefile; extra == "full"
Dynamic: license-file
